[
  {
    "id" : 1,
    "question": "Which of these drivers will have the fastest lap by the end of Stage 2?",
    "answers":  [
      "Ryan Blaney",
      "Martin Truex Jr",
      "Chase Elliot",
      "Denny Hamlin",
      "Joey Logano",
      "Kevin Harvick"
    ],
    "chosen" : null
  },
  {
    "id" : 2,
    "question": "Of the 4 winners this season, who will have the best finish in Stage 2?",
    "answers": [
      "Christopher Bell",
      "William Byron",
      "Kyle Larson",
      "Michael McDowell"
    ],
    "chosen" : null
  }
]